gjcode/__init__.py
gjcode/rand.py
gjcode/test.py
gjcode-0.0.13.dist-info/LICENSE
gjcode-0.0.13.dist-info/METADATA
gjcode-0.0.13.dist-info/WHEEL
gjcode-0.0.13.dist-info/top_level.txt
gjcode-0.0.13.dist-info/RECORD
