Metadata-Version: 2.1
Name: gjcode
Version: 0.0.13
Summary: A collection of my personal Python code
Author-email: Greg Chetcuti <greg@chetcuti.com>
License: MIT
Project-URL: Homepage, https://github.com/chetcuti/gjcode
Project-URL: Bug Tracker', https://github.com/chetcuti/gjcode/issues
Classifier: License :: OSI Approved :: MIT License
Classifier: Operating System :: OS Independent
Classifier: Programming Language :: Python
Classifier: Programming Language :: Python :: 3
Requires-Python: >=3.7
License-File: LICENSE
